webexpython/__init__.py
webexpython/webex.py
webexpython-0.2.19.dist-info/METADATA
webexpython-0.2.19.dist-info/WHEEL
webexpython-0.2.19.dist-info/top_level.txt
webexpython-0.2.19.dist-info/RECORD
