Metadata-Version: 2.1
Name: webexpython
Version: 0.2.19
Summary: Python tools for Cisco Webex
Home-page: UNKNOWN
Author: Josh Kittle - josh.kittle@gmail.com
License: MIT
Platform: UNKNOWN
Requires-Dist: requests
